odoo/addons/ddmrp_report_part_flow_index/README.rst
odoo/addons/ddmrp_report_part_flow_index/__init__.py
odoo/addons/ddmrp_report_part_flow_index/__manifest__.py
odoo/addons/ddmrp_report_part_flow_index/i18n/ddmrp_report_part_flow_index.pot
odoo/addons/ddmrp_report_part_flow_index/i18n/it.po
odoo/addons/ddmrp_report_part_flow_index/models/__init__.py
odoo/addons/ddmrp_report_part_flow_index/models/ddmrp_flow_index_group.py
odoo/addons/ddmrp_report_part_flow_index/models/stock_buffer.py
odoo/addons/ddmrp_report_part_flow_index/readme/CONFIGURE.rst
odoo/addons/ddmrp_report_part_flow_index/readme/CONTRIBUTORS.rst
odoo/addons/ddmrp_report_part_flow_index/readme/DESCRIPTION.rst
odoo/addons/ddmrp_report_part_flow_index/readme/HISTORY.rst
odoo/addons/ddmrp_report_part_flow_index/readme/ROADMAP.rst
odoo/addons/ddmrp_report_part_flow_index/readme/USAGE.rst
odoo/addons/ddmrp_report_part_flow_index/reports/__init__.py
odoo/addons/ddmrp_report_part_flow_index/reports/report_ddmrp_part_plan_flow_index.py
odoo/addons/ddmrp_report_part_flow_index/reports/report_ddmrp_part_plan_flow_index_views.xml
odoo/addons/ddmrp_report_part_flow_index/security/ir.model.access.csv
odoo/addons/ddmrp_report_part_flow_index/security/report_ddmrp_part_plan_flow_index_security.xml
odoo/addons/ddmrp_report_part_flow_index/static/description/icon.png
odoo/addons/ddmrp_report_part_flow_index/static/description/index.html
odoo/addons/ddmrp_report_part_flow_index/views/ddmrp_flow_index_group_views.xml
odoo/addons/ddmrp_report_part_flow_index/views/stock_buffer_view.xml
odoo14_addon_ddmrp_report_part_flow_index-14.0.1.3.0.dist-info/METADATA
odoo14_addon_ddmrp_report_part_flow_index-14.0.1.3.0.dist-info/WHEEL
odoo14_addon_ddmrp_report_part_flow_index-14.0.1.3.0.dist-info/top_level.txt
odoo14_addon_ddmrp_report_part_flow_index-14.0.1.3.0.dist-info/RECORD
